kekflow_messages/ImagerService_pb2.py
kekflow_messages/ImagerService_pb2_grpc.py
kekflow_messages/__init__.py
kekflow_messages-0.0.5.dist-info/METADATA
kekflow_messages-0.0.5.dist-info/WHEEL
kekflow_messages-0.0.5.dist-info/top_level.txt
kekflow_messages-0.0.5.dist-info/RECORD
