Metadata-Version: 2.1
Name: kekflow-messages
Version: 0.0.5
Summary: Kekflow  Utilities
Home-page: UNKNOWN
Author: Kekflow
Author-email: alex.agitolyev@gmail.com
License: UNKNOWN
Platform: UNKNOWN
Requires-Python: >=3.7
